erspy/__init__.py
erspy/main.py
erspy_dandlion-0.0.4.dist-info/METADATA
erspy_dandlion-0.0.4.dist-info/WHEEL
erspy_dandlion-0.0.4.dist-info/license
erspy_dandlion-0.0.4.dist-info/top_level.txt
erspy_dandlion-0.0.4.dist-info/RECORD
