Metadata-Version: 2.1
Name: erspy_dandlion
Version: 0.0.4
Summary: Enables networking between Python applications and Escape Room Software (ERS)
Author-email: dandlion <info@expandingeden.games>
Project-URL: Homepage, https://github.com/OrganicPepper/erspy
Project-URL: Issues, https://github.com/OrganicPepper/erspy/issues
Classifier: Programming Language :: Python :: 3
Classifier: License :: OSI Approved :: MIT License
Classifier: Operating System :: OS Independent
Requires-Python: >=3.8
License-File: license
Requires-Dist: paho-mqtt
